odoo/addons/azokoop/__manifest__.py
odoo/addons/azokoop/views/templates.xml
odoo_addon_azokoop-16.0.1.1.0.dist-info/METADATA
odoo_addon_azokoop-16.0.1.1.0.dist-info/WHEEL
odoo_addon_azokoop-16.0.1.1.0.dist-info/top_level.txt
odoo_addon_azokoop-16.0.1.1.0.dist-info/RECORD
